phois/__init__.py
phois/errors.py
phois/py.typed
phois/tlds.json
phois-0.1.0.dist-info/licenses/LICENSE
phois-0.1.0.dist-info/WHEEL
phois-0.1.0.dist-info/METADATA
phois-0.1.0.dist-info/RECORD
