Metadata-Version: 2.4
Name: Phois
Version: 0.1.0
Summary: Whois lookup using Proxy
Author: Mirhossein Mousavi
Author-email: Mirhossein Mousavi <mr.mousavi@live.com>
License-Expression: MIT
License-File: LICENSE
Requires-Dist: chardet>=5.2.0
Requires-Dist: pysocks>=1.7.1
Requires-Dist: tldextract>=5.3.1
Requires-Python: >=3.13
Project-URL: HomePage, https://github.com/mirhmousavi/Phois
Project-URL: Issues, https://github.com/mirhmousavi/Phois/issues
